followthemoney_compare/__init__.py
followthemoney_compare/cli.py
followthemoney_compare/compare.py
followthemoney_compare/lib/__init__.py
followthemoney_compare/lib/profiles.py
followthemoney_compare/lib/utils.py
followthemoney_compare/lib/word_frequency.py
followthemoney_compare/metrics/__init__.py
followthemoney_compare/metrics/common.py
followthemoney_compare/metrics/countries.py
followthemoney_compare/metrics/names.py
followthemoney_compare/models/__init__.py
followthemoney_compare/models/glm_bernoulli.py
followthemoney_compare/models/glm_bernoulli_2e.py
followthemoney_compare/models/model_base.py
followthemoney_compare/models/pm_model_base.py
followthemoney_compare-0.4.4.dist-info/METADATA
followthemoney_compare-0.4.4.dist-info/WHEEL
followthemoney_compare-0.4.4.dist-info/entry_points.txt
followthemoney_compare-0.4.4.dist-info/namespace_packages.txt
followthemoney_compare-0.4.4.dist-info/top_level.txt
followthemoney_compare-0.4.4.dist-info/RECORD
