Metadata-Version: 2.1
Name: followthemoney-compare
Version: 0.4.4
Summary: UNKNOWN
Home-page: https://github.com/alephdata/followthemoney-compare/
Author: Organized Crime and Corruption Reporting Project
Author-email: data@occrp.org
License: MIT
Platform: UNKNOWN
Requires-Dist: click (>=7.0)
Requires-Dist: numpy (>=1.20.0)
Requires-Dist: pandas (>=1.2.2)
Requires-Dist: followthemoney (>=3.0.4)
Requires-Dist: fuzzywuzzy[speedup] (<1.0.0,>=0.18.0)
Requires-Dist: tqdm (>=4.50.0)
Requires-Dist: mmh3
Provides-Extra: dev
Requires-Dist: pymc3 (>=3.11.2) ; extra == 'dev'
Requires-Dist: scikit-learn (>=0.24.1) ; extra == 'dev'
Requires-Dist: matplotlib (>=3.4.1) ; extra == 'dev'
Requires-Dist: seaborn (>=0.11.1) ; extra == 'dev'
Requires-Dist: arviz (>=0.11.2) ; extra == 'dev'
